LICENSE
MANIFEST.in
README.md
VERSION
requirements.txt
setup.cfg
setup.py
src/airctrl/__init__.py
src/airctrl/communicator.py
src/airctrl/console.py
src/airctrl/environment.py
src/airctrl/sample_generator.py
src/airctrl.egg-info/PKG-INFO
src/airctrl.egg-info/SOURCES.txt
src/airctrl.egg-info/dependency_links.txt
src/airctrl.egg-info/entry_points.txt
src/airctrl.egg-info/requires.txt
src/airctrl.egg-info/top_level.txt
src/airctrl/utils/__init__.py
src/airctrl/utils/unity.py