Metadata-Version: 2.1
Name: airctrl
Version: 1.3.2
Summary: AirControl is an Open Source, Modular, Cross-Platform, and Extensible Flight Simulator For Deep Learning Research.
Home-page: https://aircontrol.readthedocs.io
Author: Sunil Patel
Author-email: snlpatel001213@hotmail.com
License: UNKNOWN
Project-URL: Source, https://github.com/snlpatel001213/AirControl/
Project-URL: Bug Reports, https://github.com/snlpatel001213/AirControl/issues
Project-URL: Release Plan, https://github.com/snlpatel001213/AirControl/projects/1
Keywords: Airplane Simulation,Unity,C#,Python
Platform: UNKNOWN
Classifier: Development Status :: 5 - Production/Stable
Classifier: Intended Audience :: Developers
Classifier: Operating System :: OS Independent
Classifier: Topic :: Education
Classifier: Topic :: Scientific/Engineering
Classifier: Topic :: Scientific/Engineering :: Artificial Intelligence
Classifier: Topic :: Scientific/Engineering :: Image Recognition
Classifier: License :: OSI Approved :: GNU General Public License v3 (GPLv3)
Classifier: Programming Language :: Python :: 3.7
Classifier: Programming Language :: Python :: 3.8
Classifier: Programming Language :: Python :: 3.9
Requires-Python: >=3.7, <4
